yirabot/__init__.py
yirabot/crawling_functions.py
yirabot/data_extraction_functions.py
yirabot/display_functions.py
yirabot/errors.py
yirabot/help.py
yirabot/helper_functions.py
yirabot/saving_functions.py
yirabot/seo_functions.py
yirabot/yirabot.py
YiraBot-1.0.9.2.dist-info/LICENSE
YiraBot-1.0.9.2.dist-info/METADATA
YiraBot-1.0.9.2.dist-info/WHEEL
YiraBot-1.0.9.2.dist-info/entry_points.txt
YiraBot-1.0.9.2.dist-info/top_level.txt
YiraBot-1.0.9.2.dist-info/RECORD
