Metadata-Version: 2.1
Name: YiraBot
Version: 1.0.9.2
Summary: YiraBot: Simplifying Web Scraping for All. A user-friendly tool for developers and enthusiasts, offering command-line ease and Python integration. Ideal for research, SEO, and data collection.
Home-page: https://github.com/OwenOrcan/Yirabot-Crawler
Author: Owen Orcan
Author-email: owenorcan@gmail.com
License: GNU General Public License (Version 3)
License-File: LICENSE
Requires-Dist: beautifulsoup4 ==4.12.3
Requires-Dist: Requests ==2.31.0
Requires-Dist: rich ==13.7.0
Requires-Dist: html5lib ==1.1
